bloggerer/__init__.py
bloggerer/pf.py
bloggerer-0.9.dist-info/AUTHORS
bloggerer-0.9.dist-info/LICENSE
bloggerer-0.9.dist-info/METADATA
bloggerer-0.9.dist-info/WHEEL
bloggerer-0.9.dist-info/entry_points.txt
bloggerer-0.9.dist-info/top_level.txt
bloggerer-0.9.dist-info/RECORD
