Metadata-Version: 2.1
Name: bloggerer
Version: 0.9
Summary: Transforms markdown (and probably other things too) into WordPress-compatible "Custom HTML" with pandoc and additional magic.
Author-email: Jeff Dileo <jtdileo@gmail.com>
Maintainer-email: Jeff Dileo <jtdileo@gmail.com>
License: Copyright (c) 2020-2022 NCC Group,
Project-URL: repository, https://github.com/ChaosData/bloggerer
Keywords: pandoc,panflute,markdown,wordpress,html
Classifier: License :: OSI Approved :: BSD License
Classifier: Programming Language :: Python :: 3.6
Requires-Python: >=3.6
License-File: LICENSE
License-File: AUTHORS
Requires-Dist: panflute
Requires-Dist: pillow
